{
  "cli": {
    "version": ">= 16.28.0",
    "appVersionSource": "remote"
  },
  "build": {
    "development": {
      "developmentClient": true,
      "distribution": "internal"
    },
    "preview": {
      "android": {
        "buildType": "apk"
      },
      "distribution": "internal",
      "env": {
        "API_BASE_URL": "http://10.177.119.107:8000"
      }
    },
    "production": {
      "android": {
        "buildType": "app-bundle"
      },
      "distribution": "store",
      "autoIncrement": true
    }
  },
  "submit": {
    "production": {}
  }
}
